pypme/__init__.py
pypme/mod_tessa_pme.py
pypme/pme.py
pypme-0.7.0.dist-info/LICENSE
pypme-0.7.0.dist-info/METADATA
pypme-0.7.0.dist-info/WHEEL
pypme-0.7.0.dist-info/RECORD
