Metadata-Version: 2.3
Name: pypme
Version: 0.7.0
Summary: Python package for PME (Public Market Equivalent) calculation
License: MIT
Keywords: python,finance,investing,financial-analysis,pme,investment-analysis
Author: ymyke
Requires-Python: >=3.10,<4.0
Classifier: License :: OSI Approved :: MIT License
Classifier: Programming Language :: Python :: 3
Classifier: Programming Language :: Python :: 3.10
Classifier: Programming Language :: Python :: 3.11
Classifier: Programming Language :: Python :: 3.12
Classifier: Programming Language :: Python :: 3.13
Requires-Dist: numpy-financial (>=1.0)
Requires-Dist: pandas (>=2.2)
Requires-Dist: tessa (>=0.9)
Requires-Dist: xirr (>=0.1)
Project-URL: Homepage, https://github.com/ymyke/pypme
Project-URL: Repository, https://github.com/ymyke/pypme
